{"_type":"export","__export_format":4,"__export_date":"2023-01-12T11:57:20.080Z","__export_source":"clickmvp:v2022.1.0.0","resources":[{"_id":"wrk_46703ad94c413e29ffa24f25275d130d","parentId":null,"modified":1673535440081,"created":1673535440081,"name":"basic","description":"B\u00e1sico","scope":"collection","_type":"workspace"},{"_id":"env_255a32b46352fe3eab36b067b4d54c2f","parentId":"wrk_46703ad94c413e29ffa24f25275d130d","modified":1673535440081,"created":1673535440081,"name":"root","data":{"baseUrl":"http:\/\/localhost:3333"},"dataPropertyOrder":{"&":["baseUrl","token"]},"color":null,"isPrivate":false,"metaSortKey":1673535440081,"_type":"environment"},{"_id":"fld_5d3f997a2457834034290eeb87014fea","parentId":"wrk_46703ad94c413e29ffa24f25275d130d","modified":1673535440081,"created":1673535440081,"name":"Authentication","description":"","environment":[],"environmentPropertyOrder":null,"metaSortKey":0,"_type":"request_group"},{"_id":"fld_120d12c3020b622765a32feaf88be212","parentId":"fld_5d3f997a2457834034290eeb87014fea","modified":1673535440081,"created":1673535440081,"name":"Users","description":"","environment":[],"environmentPropertyOrder":null,"metaSortKey":1,"_type":"request_group"},{"_id":"req_55a61c213d33113dbc7321420d81be9b","parentId":"fld_120d12c3020b622765a32feaf88be212","modified":1673535440081,"created":1673535440081,"url":"{{ _.baseUrl }}\/users","name":"Create","description":"","method":"POST","body":{"mimeType":"application\/json","text":"{\n\t\"name\": \"Admin\",\n\t\"email\": \"admin@basic.com.br\",\n\t\"password\": \"admin\"\n}"},"parameters":[],"headers":[{"name":"Content-Type","value":"application\/json","id":"pair_368da9cd5caf4894bdbec66ac89d0a29"}],"authentication":[],"metaSortKey":2,"isPrivate":false,"settingStoreCookies":true,"settingSendCookies":true,"settingDisableRenderRequestBody":false,"settingEncodeUrl":true,"settingRebuildPath":true,"settingFollowRedirects":"global","_type":"request"},{"_id":"req_7ea653561d854b6e86c806b3c57b9982","parentId":"fld_120d12c3020b622765a32feaf88be212","modified":1673535440081,"created":1673535440081,"url":"{{ _.baseUrl }}\/sessions","name":"Session","description":"","method":"POST","body":{"mimeType":"application\/json","text":"{\n\t\"email\": \"admin@basic.com.br\",\n\t\"password\": \"admin\"\n}"},"parameters":[],"headers":[{"name":"Content-Type","value":"application\/json","id":"pair_e1cc7c536356ccd9a3ad1f7fc6349b88"}],"authentication":[],"metaSortKey":3,"isPrivate":false,"settingStoreCookies":true,"settingSendCookies":true,"settingDisableRenderRequestBody":false,"settingEncodeUrl":true,"settingRebuildPath":true,"settingFollowRedirects":"global","_type":"request"},{"_id":"fld_108c4811e839aaf331c43448bec07c05","parentId":"fld_5d3f997a2457834034290eeb87014fea","modified":1673535440081,"created":1673535440081,"name":"Passwords","description":"","environment":[],"environmentPropertyOrder":null,"metaSortKey":4,"_type":"request_group"},{"_id":"req_f652e9a00d83d58ca95e7c81158a1436","parentId":"fld_108c4811e839aaf331c43448bec07c05","modified":1673535440081,"created":1673535440081,"url":"{{ _.baseUrl }}\/passwords\/forgot","name":"Forgot","description":"","method":"POST","body":{"mimeType":"application\/json","text":"{\n\t\"email\": \"admin@basic.com.br\"\n}"},"parameters":[],"headers":[{"name":"Content-Type","value":"application\/json","id":"pair_c1cc2c854b94095085af09e219bca740"}],"authentication":[],"metaSortKey":5,"isPrivate":false,"settingStoreCookies":true,"settingSendCookies":true,"settingDisableRenderRequestBody":false,"settingEncodeUrl":true,"settingRebuildPath":true,"settingFollowRedirects":"global","_type":"request"},{"_id":"req_0c4a72cd636dd7448fa4c4a2a293b5db","parentId":"fld_108c4811e839aaf331c43448bec07c05","modified":1673535440081,"created":1673535440081,"url":"{{ _.baseUrl }}\/passwords\/reset","name":"Reset","description":"","method":"POST","body":[],"parameters":[],"headers":[],"authentication":[],"metaSortKey":6,"isPrivate":false,"settingStoreCookies":true,"settingSendCookies":true,"settingDisableRenderRequestBody":false,"settingEncodeUrl":true,"settingRebuildPath":true,"settingFollowRedirects":"global","_type":"request"},{"_id":"fld_ff5b83b2d8671df11b21f22b9894e98f","parentId":"wrk_46703ad94c413e29ffa24f25275d130d","modified":1673535440240,"created":1673535440240,"name":"Common","description":"","environment":[],"environmentPropertyOrder":null,"metaSortKey":"001","_type":"request_group"},{"_id":"fld_670fa490db41225a517d2bb3f5528269","parentId":"fld_ff5b83b2d8671df11b21f22b9894e98f","modified":1673535440240,"created":1673535440240,"name":"Estados","description":"","environment":[],"environmentPropertyOrder":null,"metaSortKey":"001001","_type":"request_group"},{"_id":"req_1311d01716ada4d0f38b01651a586916","parentId":"fld_670fa490db41225a517d2bb3f5528269","modified":1673535440240,"created":1673535440240,"url":"{{ _.baseUrl }}\/estados","name":"Create","description":"","method":"POST","body":{"mimeType":"application\/json","text":"{\n\t\"nome\": \"Nome de estados\",\n\t\"uf\": \"Uf de estados\"\n}"},"parameters":[],"headers":[{"name":"Content-Type","value":"application\/json","id":"pair_205d3c81c3f1cbbfcf24a26d1c569f4a"}],"authentication":{"type":"bearer","token":"{% response 'body', 'req_7ea653561d854b6e86c806b3c57b9982', 'b64::JC50b2tlbg==::46b', 'never', 60 %}"},"metaSortKey":10,"isPrivate":false,"settingStoreCookies":true,"settingSendCookies":true,"settingDisableRenderRequestBody":false,"settingEncodeUrl":true,"settingRebuildPath":true,"settingFollowRedirects":"global","_type":"request"},{"_id":"req_79ef1136301ea7a628caf1125d59295d","parentId":"fld_670fa490db41225a517d2bb3f5528269","modified":1673535440240,"created":1673535440240,"url":"{{ _.baseUrl }}\/estados\/select","name":"Select","description":"","method":"POST","body":[],"parameters":[],"headers":[{"name":"Content-Type","value":"application\/json","id":"pair_f3b703b4ef67edb5a5f43cefde055748"}],"authentication":{"type":"bearer","token":"{% response 'body', 'req_7ea653561d854b6e86c806b3c57b9982', 'b64::JC50b2tlbg==::46b', 'never', 60 %}"},"metaSortKey":30,"isPrivate":false,"settingStoreCookies":true,"settingSendCookies":true,"settingDisableRenderRequestBody":false,"settingEncodeUrl":true,"settingRebuildPath":true,"settingFollowRedirects":"global","_type":"request"},{"_id":"req_e772e24677b99ba3966a1f7d81d8170a","parentId":"fld_670fa490db41225a517d2bb3f5528269","modified":1673535440240,"created":1673535440240,"url":"{{ _.baseUrl }}\/estados\/list","name":"List","description":"","method":"POST","body":{"mimeType":"application\/json","text":"{\n\t\"search\": \"\",\n\t\"rowsPerPage\": 10,\n\t\"page\": 0,\n\t\"columnOrder\": [\"ASC\", \"ASC\"]\n}"},"parameters":[],"headers":[{"name":"Content-Type","value":"application\/json","id":"pair_8649928da2a7b36e8d00fca9b858bfd1"}],"authentication":{"type":"bearer","token":"{% response 'body', 'req_7ea653561d854b6e86c806b3c57b9982', 'b64::JC50b2tlbg==::46b', 'never', 60 %}"},"metaSortKey":20,"isPrivate":false,"settingStoreCookies":true,"settingSendCookies":true,"settingDisableRenderRequestBody":false,"settingEncodeUrl":true,"settingRebuildPath":true,"settingFollowRedirects":"global","_type":"request"},{"_id":"req_8d4197915d136c451b5418783320987f","parentId":"fld_670fa490db41225a517d2bb3f5528269","modified":1673535440240,"created":1673535440240,"url":"{{ _.baseUrl }}\/estados\/count","name":"Count","description":"","method":"POST","body":{"mimeType":"application\/json","text":"{\n\t\"search\": \"\"\n}"},"parameters":[],"headers":[{"name":"Content-Type","value":"application\/json","id":"pair_4d10b1fe0d117877af371d2c608dd388"}],"authentication":{"type":"bearer","token":"{% response 'body', 'req_7ea653561d854b6e86c806b3c57b9982', 'b64::JC50b2tlbg==::46b', 'never', 60 %}"},"metaSortKey":40,"isPrivate":false,"settingStoreCookies":true,"settingSendCookies":true,"settingDisableRenderRequestBody":false,"settingEncodeUrl":true,"settingRebuildPath":true,"settingFollowRedirects":"global","_type":"request"},{"_id":"req_215c5011faeee57a8e35c9a4d9920f0b","parentId":"fld_670fa490db41225a517d2bb3f5528269","modified":1673535440240,"created":1673535440240,"url":"{{ _.baseUrl }}\/estados\/1d47e758-718f-4f8e-8d00-9199d3900cf5","name":"Get","description":"","method":"GET","body":[],"parameters":[],"headers":[],"authentication":{"type":"bearer","token":"{% response 'body', 'req_7ea653561d854b6e86c806b3c57b9982', 'b64::JC50b2tlbg==::46b', 'never', 60 %}"},"metaSortKey":50,"isPrivate":false,"settingStoreCookies":true,"settingSendCookies":true,"settingDisableRenderRequestBody":false,"settingEncodeUrl":true,"settingRebuildPath":true,"settingFollowRedirects":"global","_type":"request"},{"_id":"req_1e716d1089dd59b2b1abd99e30206fc9","parentId":"fld_670fa490db41225a517d2bb3f5528269","modified":1673535440240,"created":1673535440240,"url":"{{ _.baseUrl }}\/estados","name":"Update","description":"","method":"PUT","body":{"mimeType":"application\/json","text":"{\n\t\"id\": \"1d47e758-718f-4f8e-8d00-9199d3900cf5\",\n\t\"nome\": \"Nome de estados\",\n\t\"uf\": \"Uf de estados\"\n}"},"parameters":[],"headers":[{"name":"Content-Type","value":"application\/json","id":"pair_97e5b27330046ab588fe78193657af0a"}],"authentication":{"type":"bearer","token":"{% response 'body', 'req_7ea653561d854b6e86c806b3c57b9982', 'b64::JC50b2tlbg==::46b', 'never', 60 %}"},"metaSortKey":60,"isPrivate":false,"settingStoreCookies":true,"settingSendCookies":true,"settingDisableRenderRequestBody":false,"settingEncodeUrl":true,"settingRebuildPath":true,"settingFollowRedirects":"global","_type":"request"},{"_id":"req_8a1e5ef70740340c52fd6dcb0d730159","parentId":"fld_670fa490db41225a517d2bb3f5528269","modified":1673535440240,"created":1673535440240,"url":"{{ _.baseUrl }}\/estados\/1d47e758-718f-4f8e-8d00-9199d3900cf5","name":"Delete","description":"","method":"DELETE","body":[],"parameters":[],"headers":[],"authentication":{"type":"bearer","token":"{% response 'body', 'req_7ea653561d854b6e86c806b3c57b9982', 'b64::JC50b2tlbg==::46b', 'never', 60 %}"},"metaSortKey":70,"isPrivate":false,"settingStoreCookies":true,"settingSendCookies":true,"settingDisableRenderRequestBody":false,"settingEncodeUrl":true,"settingRebuildPath":true,"settingFollowRedirects":"global","_type":"request"},{"_id":"fld_6121961558b94981d7bb420efc6027f1","parentId":"fld_ff5b83b2d8671df11b21f22b9894e98f","modified":1673535440240,"created":1673535440240,"name":"Cidades","description":"","environment":[],"environmentPropertyOrder":null,"metaSortKey":"001002","_type":"request_group"},{"_id":"req_298da42633d559e485d02e3bb8813886","parentId":"fld_6121961558b94981d7bb420efc6027f1","modified":1673535440240,"created":1673535440240,"url":"{{ _.baseUrl }}\/cidades","name":"Create","description":"","method":"POST","body":{"mimeType":"application\/json","text":"{\n\t\"nome\": \"Nome de cidades\",\n\t\"estadoId\": null\n}"},"parameters":[],"headers":[{"name":"Content-Type","value":"application\/json","id":"pair_fe5ee0f3cbc847f3c4c0986eb642b12b"}],"authentication":{"type":"bearer","token":"{% response 'body', 'req_7ea653561d854b6e86c806b3c57b9982', 'b64::JC50b2tlbg==::46b', 'never', 60 %}"},"metaSortKey":10,"isPrivate":false,"settingStoreCookies":true,"settingSendCookies":true,"settingDisableRenderRequestBody":false,"settingEncodeUrl":true,"settingRebuildPath":true,"settingFollowRedirects":"global","_type":"request"},{"_id":"req_0d7449af64663cde0f73841261329aee","parentId":"fld_6121961558b94981d7bb420efc6027f1","modified":1673535440240,"created":1673535440240,"url":"{{ _.baseUrl }}\/cidades\/select","name":"Select","description":"","method":"POST","body":[],"parameters":[],"headers":[{"name":"Content-Type","value":"application\/json","id":"pair_557d69b1184b9dc4dce64c1524e70fec"}],"authentication":{"type":"bearer","token":"{% response 'body', 'req_7ea653561d854b6e86c806b3c57b9982', 'b64::JC50b2tlbg==::46b', 'never', 60 %}"},"metaSortKey":30,"isPrivate":false,"settingStoreCookies":true,"settingSendCookies":true,"settingDisableRenderRequestBody":false,"settingEncodeUrl":true,"settingRebuildPath":true,"settingFollowRedirects":"global","_type":"request"},{"_id":"req_315153eafa7710a823abb5e38d6bfe1b","parentId":"fld_6121961558b94981d7bb420efc6027f1","modified":1673535440240,"created":1673535440240,"url":"{{ _.baseUrl }}\/cidades\/list","name":"List","description":"","method":"POST","body":{"mimeType":"application\/json","text":"{\n\t\"search\": \"\",\n\t\"rowsPerPage\": 10,\n\t\"page\": 0,\n\t\"columnOrder\": [\"ASC\", \"ASC\"]\n}"},"parameters":[],"headers":[{"name":"Content-Type","value":"application\/json","id":"pair_c0eeea971045924d02666e5fc69417d4"}],"authentication":{"type":"bearer","token":"{% response 'body', 'req_7ea653561d854b6e86c806b3c57b9982', 'b64::JC50b2tlbg==::46b', 'never', 60 %}"},"metaSortKey":20,"isPrivate":false,"settingStoreCookies":true,"settingSendCookies":true,"settingDisableRenderRequestBody":false,"settingEncodeUrl":true,"settingRebuildPath":true,"settingFollowRedirects":"global","_type":"request"},{"_id":"req_e27ea92e87c35dd3f12dc24871218711","parentId":"fld_6121961558b94981d7bb420efc6027f1","modified":1673535440240,"created":1673535440240,"url":"{{ _.baseUrl }}\/cidades\/count","name":"Count","description":"","method":"POST","body":{"mimeType":"application\/json","text":"{\n\t\"search\": \"\"\n}"},"parameters":[],"headers":[{"name":"Content-Type","value":"application\/json","id":"pair_84438befadc0c5604dcf4ff6c5d3f1ba"}],"authentication":{"type":"bearer","token":"{% response 'body', 'req_7ea653561d854b6e86c806b3c57b9982', 'b64::JC50b2tlbg==::46b', 'never', 60 %}"},"metaSortKey":40,"isPrivate":false,"settingStoreCookies":true,"settingSendCookies":true,"settingDisableRenderRequestBody":false,"settingEncodeUrl":true,"settingRebuildPath":true,"settingFollowRedirects":"global","_type":"request"},{"_id":"req_82bde9046cb7c44f44d26b43e65cc45b","parentId":"fld_6121961558b94981d7bb420efc6027f1","modified":1673535440240,"created":1673535440240,"url":"{{ _.baseUrl }}\/cidades\/1d47e758-718f-4f8e-8d00-9199d3900cf5","name":"Get","description":"","method":"GET","body":[],"parameters":[],"headers":[],"authentication":{"type":"bearer","token":"{% response 'body', 'req_7ea653561d854b6e86c806b3c57b9982', 'b64::JC50b2tlbg==::46b', 'never', 60 %}"},"metaSortKey":50,"isPrivate":false,"settingStoreCookies":true,"settingSendCookies":true,"settingDisableRenderRequestBody":false,"settingEncodeUrl":true,"settingRebuildPath":true,"settingFollowRedirects":"global","_type":"request"},{"_id":"req_184189f20bde1084b8a6f4a91649036b","parentId":"fld_6121961558b94981d7bb420efc6027f1","modified":1673535440240,"created":1673535440240,"url":"{{ _.baseUrl }}\/cidades","name":"Update","description":"","method":"PUT","body":{"mimeType":"application\/json","text":"{\n\t\"id\": \"1d47e758-718f-4f8e-8d00-9199d3900cf5\",\n\t\"nome\": \"Nome de cidades\",\n\t\"estadoId\": null\n}"},"parameters":[],"headers":[{"name":"Content-Type","value":"application\/json","id":"pair_1ddd07076d68d6486d5eefea5911c57c"}],"authentication":{"type":"bearer","token":"{% response 'body', 'req_7ea653561d854b6e86c806b3c57b9982', 'b64::JC50b2tlbg==::46b', 'never', 60 %}"},"metaSortKey":60,"isPrivate":false,"settingStoreCookies":true,"settingSendCookies":true,"settingDisableRenderRequestBody":false,"settingEncodeUrl":true,"settingRebuildPath":true,"settingFollowRedirects":"global","_type":"request"},{"_id":"req_802eaecafd59165ebd1731f7ca6b9713","parentId":"fld_6121961558b94981d7bb420efc6027f1","modified":1673535440240,"created":1673535440240,"url":"{{ _.baseUrl }}\/cidades\/1d47e758-718f-4f8e-8d00-9199d3900cf5","name":"Delete","description":"","method":"DELETE","body":[],"parameters":[],"headers":[],"authentication":{"type":"bearer","token":"{% response 'body', 'req_7ea653561d854b6e86c806b3c57b9982', 'b64::JC50b2tlbg==::46b', 'never', 60 %}"},"metaSortKey":70,"isPrivate":false,"settingStoreCookies":true,"settingSendCookies":true,"settingDisableRenderRequestBody":false,"settingEncodeUrl":true,"settingRebuildPath":true,"settingFollowRedirects":"global","_type":"request"},{"_id":"fld_f0e5e48f4089e9f4e98667a357022293","parentId":"fld_ff5b83b2d8671df11b21f22b9894e98f","modified":1673535440240,"created":1673535440240,"name":"Clientes","description":"","environment":[],"environmentPropertyOrder":null,"metaSortKey":"001003","_type":"request_group"},{"_id":"req_7247d18138f8fe5f80e6a0717d193db2","parentId":"fld_f0e5e48f4089e9f4e98667a357022293","modified":1673535440240,"created":1673535440240,"url":"{{ _.baseUrl }}\/clientes","name":"Create","description":"","method":"POST","body":{"mimeType":"application\/json","text":"{\n\t\"nome\": \"Nome de clientes\",\n\t\"estadoId\": null,\n\t\"cidadeId\": null\n}"},"parameters":[],"headers":[{"name":"Content-Type","value":"application\/json","id":"pair_1b5ba1a35d120ebd3c6864cf0146c354"}],"authentication":{"type":"bearer","token":"{% response 'body', 'req_7ea653561d854b6e86c806b3c57b9982', 'b64::JC50b2tlbg==::46b', 'never', 60 %}"},"metaSortKey":10,"isPrivate":false,"settingStoreCookies":true,"settingSendCookies":true,"settingDisableRenderRequestBody":false,"settingEncodeUrl":true,"settingRebuildPath":true,"settingFollowRedirects":"global","_type":"request"},{"_id":"req_31fac43f84c897a641ca61c797aabeb5","parentId":"fld_f0e5e48f4089e9f4e98667a357022293","modified":1673535440240,"created":1673535440240,"url":"{{ _.baseUrl }}\/clientes\/select","name":"Select","description":"","method":"POST","body":[],"parameters":[],"headers":[{"name":"Content-Type","value":"application\/json","id":"pair_c7223487272f6500bca1f344ec6cfbb6"}],"authentication":{"type":"bearer","token":"{% response 'body', 'req_7ea653561d854b6e86c806b3c57b9982', 'b64::JC50b2tlbg==::46b', 'never', 60 %}"},"metaSortKey":30,"isPrivate":false,"settingStoreCookies":true,"settingSendCookies":true,"settingDisableRenderRequestBody":false,"settingEncodeUrl":true,"settingRebuildPath":true,"settingFollowRedirects":"global","_type":"request"},{"_id":"req_3682ed6f58749501c4fba3080c67515d","parentId":"fld_f0e5e48f4089e9f4e98667a357022293","modified":1673535440240,"created":1673535440240,"url":"{{ _.baseUrl }}\/clientes\/list","name":"List","description":"","method":"POST","body":{"mimeType":"application\/json","text":"{\n\t\"search\": \"\",\n\t\"rowsPerPage\": 10,\n\t\"page\": 0,\n\t\"columnOrder\": [\"ASC\", \"ASC\"]\n}"},"parameters":[],"headers":[{"name":"Content-Type","value":"application\/json","id":"pair_8be3917898f7be4f1289928dafda9468"}],"authentication":{"type":"bearer","token":"{% response 'body', 'req_7ea653561d854b6e86c806b3c57b9982', 'b64::JC50b2tlbg==::46b', 'never', 60 %}"},"metaSortKey":20,"isPrivate":false,"settingStoreCookies":true,"settingSendCookies":true,"settingDisableRenderRequestBody":false,"settingEncodeUrl":true,"settingRebuildPath":true,"settingFollowRedirects":"global","_type":"request"},{"_id":"req_7532491deee6fb14c432a08a4702271b","parentId":"fld_f0e5e48f4089e9f4e98667a357022293","modified":1673535440240,"created":1673535440240,"url":"{{ _.baseUrl }}\/clientes\/count","name":"Count","description":"","method":"POST","body":{"mimeType":"application\/json","text":"{\n\t\"search\": \"\"\n}"},"parameters":[],"headers":[{"name":"Content-Type","value":"application\/json","id":"pair_a74e7536b3d866d4b28fdf8497a70822"}],"authentication":{"type":"bearer","token":"{% response 'body', 'req_7ea653561d854b6e86c806b3c57b9982', 'b64::JC50b2tlbg==::46b', 'never', 60 %}"},"metaSortKey":40,"isPrivate":false,"settingStoreCookies":true,"settingSendCookies":true,"settingDisableRenderRequestBody":false,"settingEncodeUrl":true,"settingRebuildPath":true,"settingFollowRedirects":"global","_type":"request"},{"_id":"req_193668815a53faad7fa56af5d2136fd9","parentId":"fld_f0e5e48f4089e9f4e98667a357022293","modified":1673535440240,"created":1673535440240,"url":"{{ _.baseUrl }}\/clientes\/1d47e758-718f-4f8e-8d00-9199d3900cf5","name":"Get","description":"","method":"GET","body":[],"parameters":[],"headers":[],"authentication":{"type":"bearer","token":"{% response 'body', 'req_7ea653561d854b6e86c806b3c57b9982', 'b64::JC50b2tlbg==::46b', 'never', 60 %}"},"metaSortKey":50,"isPrivate":false,"settingStoreCookies":true,"settingSendCookies":true,"settingDisableRenderRequestBody":false,"settingEncodeUrl":true,"settingRebuildPath":true,"settingFollowRedirects":"global","_type":"request"},{"_id":"req_cdb9d21f5d79e5ac99c87ce0cd2d2181","parentId":"fld_f0e5e48f4089e9f4e98667a357022293","modified":1673535440240,"created":1673535440240,"url":"{{ _.baseUrl }}\/clientes","name":"Update","description":"","method":"PUT","body":{"mimeType":"application\/json","text":"{\n\t\"id\": \"1d47e758-718f-4f8e-8d00-9199d3900cf5\",\n\t\"nome\": \"Nome de clientes\",\n\t\"estadoId\": null,\n\t\"cidadeId\": null\n}"},"parameters":[],"headers":[{"name":"Content-Type","value":"application\/json","id":"pair_7045e092092cd86e93c5a375045c2721"}],"authentication":{"type":"bearer","token":"{% response 'body', 'req_7ea653561d854b6e86c806b3c57b9982', 'b64::JC50b2tlbg==::46b', 'never', 60 %}"},"metaSortKey":60,"isPrivate":false,"settingStoreCookies":true,"settingSendCookies":true,"settingDisableRenderRequestBody":false,"settingEncodeUrl":true,"settingRebuildPath":true,"settingFollowRedirects":"global","_type":"request"},{"_id":"req_85afd00897cab27735e786dbf2f2d684","parentId":"fld_f0e5e48f4089e9f4e98667a357022293","modified":1673535440240,"created":1673535440240,"url":"{{ _.baseUrl }}\/clientes\/1d47e758-718f-4f8e-8d00-9199d3900cf5","name":"Delete","description":"","method":"DELETE","body":[],"parameters":[],"headers":[],"authentication":{"type":"bearer","token":"{% response 'body', 'req_7ea653561d854b6e86c806b3c57b9982', 'b64::JC50b2tlbg==::46b', 'never', 60 %}"},"metaSortKey":70,"isPrivate":false,"settingStoreCookies":true,"settingSendCookies":true,"settingDisableRenderRequestBody":false,"settingEncodeUrl":true,"settingRebuildPath":true,"settingFollowRedirects":"global","_type":"request"},{"_id":"fld_a4a6c4454c2a5ac25870c411db2922e3","parentId":"wrk_46703ad94c413e29ffa24f25275d130d","modified":1673535440240,"created":1673535440240,"name":"Security","description":"","environment":[],"environmentPropertyOrder":null,"metaSortKey":"999","_type":"request_group"},{"_id":"fld_87a28ef8d91effe9c46e3815aa6f3298","parentId":"fld_a4a6c4454c2a5ac25870c411db2922e3","modified":1673535440240,"created":1673535440240,"name":"Modules","description":"","environment":[],"environmentPropertyOrder":null,"metaSortKey":"999001","_type":"request_group"},{"_id":"req_aac46fc91fb8e2cabf3b547a97c7498c","parentId":"fld_87a28ef8d91effe9c46e3815aa6f3298","modified":1673535440240,"created":1673535440240,"url":"{{ _.baseUrl }}\/modules","name":"Create","description":"","method":"POST","body":{"mimeType":"application\/json","text":"{\n\t\"name\": \"Nome de m\u00f3dulos\",\n\t\"disabled\": 1\n}"},"parameters":[],"headers":[{"name":"Content-Type","value":"application\/json","id":"pair_bff3195aea47436b5804d2da1cdfa321"}],"authentication":{"type":"bearer","token":"{% response 'body', 'req_7ea653561d854b6e86c806b3c57b9982', 'b64::JC50b2tlbg==::46b', 'never', 60 %}"},"metaSortKey":10,"isPrivate":false,"settingStoreCookies":true,"settingSendCookies":true,"settingDisableRenderRequestBody":false,"settingEncodeUrl":true,"settingRebuildPath":true,"settingFollowRedirects":"global","_type":"request"},{"_id":"req_73d61978e361d938ace2ae5985482c17","parentId":"fld_87a28ef8d91effe9c46e3815aa6f3298","modified":1673535440240,"created":1673535440240,"url":"{{ _.baseUrl }}\/modules\/select","name":"Select","description":"","method":"POST","body":[],"parameters":[],"headers":[{"name":"Content-Type","value":"application\/json","id":"pair_06713ccbadeba8c9205a35ab420e1c5b"}],"authentication":{"type":"bearer","token":"{% response 'body', 'req_7ea653561d854b6e86c806b3c57b9982', 'b64::JC50b2tlbg==::46b', 'never', 60 %}"},"metaSortKey":30,"isPrivate":false,"settingStoreCookies":true,"settingSendCookies":true,"settingDisableRenderRequestBody":false,"settingEncodeUrl":true,"settingRebuildPath":true,"settingFollowRedirects":"global","_type":"request"},{"_id":"req_b32015e3491c32a45c33a312bc2075c9","parentId":"fld_87a28ef8d91effe9c46e3815aa6f3298","modified":1673535440240,"created":1673535440240,"url":"{{ _.baseUrl }}\/modules\/list","name":"List","description":"","method":"POST","body":{"mimeType":"application\/json","text":"{\n\t\"search\": \"\",\n\t\"rowsPerPage\": 10,\n\t\"page\": 0,\n\t\"columnOrder\": [\"ASC\", \"ASC\"]\n}"},"parameters":[],"headers":[{"name":"Content-Type","value":"application\/json","id":"pair_e0b6a547d65ca699ed5bd7b6d67096f8"}],"authentication":{"type":"bearer","token":"{% response 'body', 'req_7ea653561d854b6e86c806b3c57b9982', 'b64::JC50b2tlbg==::46b', 'never', 60 %}"},"metaSortKey":20,"isPrivate":false,"settingStoreCookies":true,"settingSendCookies":true,"settingDisableRenderRequestBody":false,"settingEncodeUrl":true,"settingRebuildPath":true,"settingFollowRedirects":"global","_type":"request"},{"_id":"req_3cd146efc8ac2d684516315e89f56513","parentId":"fld_87a28ef8d91effe9c46e3815aa6f3298","modified":1673535440240,"created":1673535440240,"url":"{{ _.baseUrl }}\/modules\/count","name":"Count","description":"","method":"POST","body":{"mimeType":"application\/json","text":"{\n\t\"search\": \"\"\n}"},"parameters":[],"headers":[{"name":"Content-Type","value":"application\/json","id":"pair_40c0ed64a58ee91132678dea4b0324cb"}],"authentication":{"type":"bearer","token":"{% response 'body', 'req_7ea653561d854b6e86c806b3c57b9982', 'b64::JC50b2tlbg==::46b', 'never', 60 %}"},"metaSortKey":40,"isPrivate":false,"settingStoreCookies":true,"settingSendCookies":true,"settingDisableRenderRequestBody":false,"settingEncodeUrl":true,"settingRebuildPath":true,"settingFollowRedirects":"global","_type":"request"},{"_id":"req_f3e604e95d47026a0ad02378459a3c5e","parentId":"fld_87a28ef8d91effe9c46e3815aa6f3298","modified":1673535440240,"created":1673535440240,"url":"{{ _.baseUrl }}\/modules\/1d47e758-718f-4f8e-8d00-9199d3900cf5","name":"Get","description":"","method":"GET","body":[],"parameters":[],"headers":[],"authentication":{"type":"bearer","token":"{% response 'body', 'req_7ea653561d854b6e86c806b3c57b9982', 'b64::JC50b2tlbg==::46b', 'never', 60 %}"},"metaSortKey":50,"isPrivate":false,"settingStoreCookies":true,"settingSendCookies":true,"settingDisableRenderRequestBody":false,"settingEncodeUrl":true,"settingRebuildPath":true,"settingFollowRedirects":"global","_type":"request"},{"_id":"req_096e69e5e0c2a7d6767876bc1daad8ea","parentId":"fld_87a28ef8d91effe9c46e3815aa6f3298","modified":1673535440240,"created":1673535440240,"url":"{{ _.baseUrl }}\/modules","name":"Update","description":"","method":"PUT","body":{"mimeType":"application\/json","text":"{\n\t\"id\": \"1d47e758-718f-4f8e-8d00-9199d3900cf5\",\n\t\"name\": \"Nome de m\u00f3dulos\",\n\t\"disabled\": 1\n}"},"parameters":[],"headers":[{"name":"Content-Type","value":"application\/json","id":"pair_408f9ac1b5fb1fa0a2e8805928c0bb26"}],"authentication":{"type":"bearer","token":"{% response 'body', 'req_7ea653561d854b6e86c806b3c57b9982', 'b64::JC50b2tlbg==::46b', 'never', 60 %}"},"metaSortKey":60,"isPrivate":false,"settingStoreCookies":true,"settingSendCookies":true,"settingDisableRenderRequestBody":false,"settingEncodeUrl":true,"settingRebuildPath":true,"settingFollowRedirects":"global","_type":"request"},{"_id":"req_84e5be63e8979dcc48224e077541dfde","parentId":"fld_87a28ef8d91effe9c46e3815aa6f3298","modified":1673535440240,"created":1673535440240,"url":"{{ _.baseUrl }}\/modules\/1d47e758-718f-4f8e-8d00-9199d3900cf5","name":"Delete","description":"","method":"DELETE","body":[],"parameters":[],"headers":[],"authentication":{"type":"bearer","token":"{% response 'body', 'req_7ea653561d854b6e86c806b3c57b9982', 'b64::JC50b2tlbg==::46b', 'never', 60 %}"},"metaSortKey":70,"isPrivate":false,"settingStoreCookies":true,"settingSendCookies":true,"settingDisableRenderRequestBody":false,"settingEncodeUrl":true,"settingRebuildPath":true,"settingFollowRedirects":"global","_type":"request"},{"_id":"fld_29926955588deea0bbef346f8435e98a","parentId":"fld_a4a6c4454c2a5ac25870c411db2922e3","modified":1673535440240,"created":1673535440240,"name":"MenuOptions","description":"","environment":[],"environmentPropertyOrder":null,"metaSortKey":"999002","_type":"request_group"},{"_id":"req_95aec9a4af220bcbd390a15f5df0ae0c","parentId":"fld_29926955588deea0bbef346f8435e98a","modified":1673535440240,"created":1673535440240,"url":"{{ _.baseUrl }}\/menu-options","name":"Create","description":"","method":"POST","body":{"mimeType":"application\/json","text":"{\n\t\"moduleId\": null,\n\t\"sequence\": \"Sequ\u00eancia de op\u00e7\u00f5es de Menu\",\n\t\"label\": \"T\u00edtulo de op\u00e7\u00f5es de Menu\",\n\t\"route\": \"Rota de op\u00e7\u00f5es de Menu\",\n\t\"icon\": \"\u00cdcone de op\u00e7\u00f5es de Menu\",\n\t\"disabled\": 1\n}"},"parameters":[],"headers":[{"name":"Content-Type","value":"application\/json","id":"pair_e1f4ed090ec49a41999d3a46e0cd481a"}],"authentication":{"type":"bearer","token":"{% response 'body', 'req_7ea653561d854b6e86c806b3c57b9982', 'b64::JC50b2tlbg==::46b', 'never', 60 %}"},"metaSortKey":10,"isPrivate":false,"settingStoreCookies":true,"settingSendCookies":true,"settingDisableRenderRequestBody":false,"settingEncodeUrl":true,"settingRebuildPath":true,"settingFollowRedirects":"global","_type":"request"},{"_id":"req_3ee5f0fe45cb96b0fe8ccbad1225bbba","parentId":"fld_29926955588deea0bbef346f8435e98a","modified":1673535440240,"created":1673535440240,"url":"{{ _.baseUrl }}\/menu-options\/select","name":"Select","description":"","method":"POST","body":[],"parameters":[],"headers":[{"name":"Content-Type","value":"application\/json","id":"pair_bdda06997e0111ab2faacce9d04862c3"}],"authentication":{"type":"bearer","token":"{% response 'body', 'req_7ea653561d854b6e86c806b3c57b9982', 'b64::JC50b2tlbg==::46b', 'never', 60 %}"},"metaSortKey":30,"isPrivate":false,"settingStoreCookies":true,"settingSendCookies":true,"settingDisableRenderRequestBody":false,"settingEncodeUrl":true,"settingRebuildPath":true,"settingFollowRedirects":"global","_type":"request"},{"_id":"req_c867dce3ead25f8bf1f9ca77b2ea7845","parentId":"fld_29926955588deea0bbef346f8435e98a","modified":1673535440240,"created":1673535440240,"url":"{{ _.baseUrl }}\/menu-options\/all","name":"All","description":"","method":"POST","body":[],"parameters":[],"headers":[{"name":"Content-Type","value":"application\/json","id":"pair_89aadcca04bd58dd26981e1223bee537"}],"authentication":{"type":"bearer","token":"{% response 'body', 'req_7ea653561d854b6e86c806b3c57b9982', 'b64::JC50b2tlbg==::46b', 'never', 60 %}"},"metaSortKey":15,"isPrivate":false,"settingStoreCookies":true,"settingSendCookies":true,"settingDisableRenderRequestBody":false,"settingEncodeUrl":true,"settingRebuildPath":true,"settingFollowRedirects":"global","_type":"request"},{"_id":"req_a689c2b3d217c274524b30f768b8e089","parentId":"fld_29926955588deea0bbef346f8435e98a","modified":1673535440240,"created":1673535440240,"url":"{{ _.baseUrl }}\/menu-options\/list","name":"List","description":"","method":"POST","body":{"mimeType":"application\/json","text":"{\n\t\"search\": \"\",\n\t\"rowsPerPage\": 10,\n\t\"page\": 0,\n\t\"columnOrder\": [\"ASC\", \"ASC\"]\n}"},"parameters":[],"headers":[{"name":"Content-Type","value":"application\/json","id":"pair_98a3b46bc548e0453ca446141b682686"}],"authentication":{"type":"bearer","token":"{% response 'body', 'req_7ea653561d854b6e86c806b3c57b9982', 'b64::JC50b2tlbg==::46b', 'never', 60 %}"},"metaSortKey":20,"isPrivate":false,"settingStoreCookies":true,"settingSendCookies":true,"settingDisableRenderRequestBody":false,"settingEncodeUrl":true,"settingRebuildPath":true,"settingFollowRedirects":"global","_type":"request"},{"_id":"req_84482a425e17e8d00755a1d9e77c45d5","parentId":"fld_29926955588deea0bbef346f8435e98a","modified":1673535440240,"created":1673535440240,"url":"{{ _.baseUrl }}\/menu-options\/count","name":"Count","description":"","method":"POST","body":{"mimeType":"application\/json","text":"{\n\t\"search\": \"\"\n}"},"parameters":[],"headers":[{"name":"Content-Type","value":"application\/json","id":"pair_1bbc8926ea5b704eda7a2ad27b3f3796"}],"authentication":{"type":"bearer","token":"{% response 'body', 'req_7ea653561d854b6e86c806b3c57b9982', 'b64::JC50b2tlbg==::46b', 'never', 60 %}"},"metaSortKey":40,"isPrivate":false,"settingStoreCookies":true,"settingSendCookies":true,"settingDisableRenderRequestBody":false,"settingEncodeUrl":true,"settingRebuildPath":true,"settingFollowRedirects":"global","_type":"request"},{"_id":"req_45b263506ce9a57350af6a4dd43684df","parentId":"fld_29926955588deea0bbef346f8435e98a","modified":1673535440240,"created":1673535440240,"url":"{{ _.baseUrl }}\/menu-options\/1d47e758-718f-4f8e-8d00-9199d3900cf5","name":"Get","description":"","method":"GET","body":[],"parameters":[],"headers":[],"authentication":{"type":"bearer","token":"{% response 'body', 'req_7ea653561d854b6e86c806b3c57b9982', 'b64::JC50b2tlbg==::46b', 'never', 60 %}"},"metaSortKey":50,"isPrivate":false,"settingStoreCookies":true,"settingSendCookies":true,"settingDisableRenderRequestBody":false,"settingEncodeUrl":true,"settingRebuildPath":true,"settingFollowRedirects":"global","_type":"request"},{"_id":"req_bfcdfe66ea1ad963519e2b77ede6197b","parentId":"fld_29926955588deea0bbef346f8435e98a","modified":1673535440240,"created":1673535440240,"url":"{{ _.baseUrl }}\/menu-options","name":"Update","description":"","method":"PUT","body":{"mimeType":"application\/json","text":"{\n\t\"id\": \"1d47e758-718f-4f8e-8d00-9199d3900cf5\",\n\t\"moduleId\": null,\n\t\"sequence\": \"Sequ\u00eancia de op\u00e7\u00f5es de Menu\",\n\t\"label\": \"T\u00edtulo de op\u00e7\u00f5es de Menu\",\n\t\"route\": \"Rota de op\u00e7\u00f5es de Menu\",\n\t\"icon\": \"\u00cdcone de op\u00e7\u00f5es de Menu\",\n\t\"disabled\": 1\n}"},"parameters":[],"headers":[{"name":"Content-Type","value":"application\/json","id":"pair_1f99dda9025986bbf50b057f75d72bc5"}],"authentication":{"type":"bearer","token":"{% response 'body', 'req_7ea653561d854b6e86c806b3c57b9982', 'b64::JC50b2tlbg==::46b', 'never', 60 %}"},"metaSortKey":60,"isPrivate":false,"settingStoreCookies":true,"settingSendCookies":true,"settingDisableRenderRequestBody":false,"settingEncodeUrl":true,"settingRebuildPath":true,"settingFollowRedirects":"global","_type":"request"},{"_id":"req_c6df7cb1acf9b35ca0edd19a4987d310","parentId":"fld_29926955588deea0bbef346f8435e98a","modified":1673535440240,"created":1673535440240,"url":"{{ _.baseUrl }}\/menu-options\/1d47e758-718f-4f8e-8d00-9199d3900cf5","name":"Delete","description":"","method":"DELETE","body":[],"parameters":[],"headers":[],"authentication":{"type":"bearer","token":"{% response 'body', 'req_7ea653561d854b6e86c806b3c57b9982', 'b64::JC50b2tlbg==::46b', 'never', 60 %}"},"metaSortKey":70,"isPrivate":false,"settingStoreCookies":true,"settingSendCookies":true,"settingDisableRenderRequestBody":false,"settingEncodeUrl":true,"settingRebuildPath":true,"settingFollowRedirects":"global","_type":"request"},{"_id":"fld_272c4698dab0d3598ce10440e2cef3b5","parentId":"fld_a4a6c4454c2a5ac25870c411db2922e3","modified":1673535440240,"created":1673535440240,"name":"Profiles","description":"","environment":[],"environmentPropertyOrder":null,"metaSortKey":"999003","_type":"request_group"},{"_id":"req_483ca1cfe6f12813e2a8f6764ca47110","parentId":"fld_272c4698dab0d3598ce10440e2cef3b5","modified":1673535440240,"created":1673535440240,"url":"{{ _.baseUrl }}\/profiles","name":"Create","description":"","method":"POST","body":{"mimeType":"application\/json","text":"{\n\t\"name\": \"Nome de perfis de Usu\u00e1rio\",\n\t\"disabled\": 1\n}"},"parameters":[],"headers":[{"name":"Content-Type","value":"application\/json","id":"pair_4d2ea8516419bf0731ae6401baede081"}],"authentication":{"type":"bearer","token":"{% response 'body', 'req_7ea653561d854b6e86c806b3c57b9982', 'b64::JC50b2tlbg==::46b', 'never', 60 %}"},"metaSortKey":10,"isPrivate":false,"settingStoreCookies":true,"settingSendCookies":true,"settingDisableRenderRequestBody":false,"settingEncodeUrl":true,"settingRebuildPath":true,"settingFollowRedirects":"global","_type":"request"},{"_id":"req_0bb2c0beb6a7438ff646032a66bade0d","parentId":"fld_272c4698dab0d3598ce10440e2cef3b5","modified":1673535440240,"created":1673535440240,"url":"{{ _.baseUrl }}\/profiles\/select","name":"Select","description":"","method":"POST","body":[],"parameters":[],"headers":[{"name":"Content-Type","value":"application\/json","id":"pair_f8c6a6b6d5ef32ed5cf643ba7a174199"}],"authentication":{"type":"bearer","token":"{% response 'body', 'req_7ea653561d854b6e86c806b3c57b9982', 'b64::JC50b2tlbg==::46b', 'never', 60 %}"},"metaSortKey":30,"isPrivate":false,"settingStoreCookies":true,"settingSendCookies":true,"settingDisableRenderRequestBody":false,"settingEncodeUrl":true,"settingRebuildPath":true,"settingFollowRedirects":"global","_type":"request"},{"_id":"req_5529fe6c4d00ef5c729dfab65b15e071","parentId":"fld_272c4698dab0d3598ce10440e2cef3b5","modified":1673535440240,"created":1673535440240,"url":"{{ _.baseUrl }}\/profiles\/list","name":"List","description":"","method":"POST","body":{"mimeType":"application\/json","text":"{\n\t\"search\": \"\",\n\t\"rowsPerPage\": 10,\n\t\"page\": 0,\n\t\"columnOrder\": [\"ASC\", \"ASC\"]\n}"},"parameters":[],"headers":[{"name":"Content-Type","value":"application\/json","id":"pair_a1061d7f2b55c7d589d8c78ef9a7b400"}],"authentication":{"type":"bearer","token":"{% response 'body', 'req_7ea653561d854b6e86c806b3c57b9982', 'b64::JC50b2tlbg==::46b', 'never', 60 %}"},"metaSortKey":20,"isPrivate":false,"settingStoreCookies":true,"settingSendCookies":true,"settingDisableRenderRequestBody":false,"settingEncodeUrl":true,"settingRebuildPath":true,"settingFollowRedirects":"global","_type":"request"},{"_id":"req_7fcbb5c23e7b28167473a96cb9dacc53","parentId":"fld_272c4698dab0d3598ce10440e2cef3b5","modified":1673535440240,"created":1673535440240,"url":"{{ _.baseUrl }}\/profiles\/count","name":"Count","description":"","method":"POST","body":{"mimeType":"application\/json","text":"{\n\t\"search\": \"\"\n}"},"parameters":[],"headers":[{"name":"Content-Type","value":"application\/json","id":"pair_206d0b70f68818dbc2e600fbd19749f4"}],"authentication":{"type":"bearer","token":"{% response 'body', 'req_7ea653561d854b6e86c806b3c57b9982', 'b64::JC50b2tlbg==::46b', 'never', 60 %}"},"metaSortKey":40,"isPrivate":false,"settingStoreCookies":true,"settingSendCookies":true,"settingDisableRenderRequestBody":false,"settingEncodeUrl":true,"settingRebuildPath":true,"settingFollowRedirects":"global","_type":"request"},{"_id":"req_4baf5e9bf5a79b50f2d69e1b21658dd6","parentId":"fld_272c4698dab0d3598ce10440e2cef3b5","modified":1673535440240,"created":1673535440240,"url":"{{ _.baseUrl }}\/profiles\/1d47e758-718f-4f8e-8d00-9199d3900cf5","name":"Get","description":"","method":"GET","body":[],"parameters":[],"headers":[],"authentication":{"type":"bearer","token":"{% response 'body', 'req_7ea653561d854b6e86c806b3c57b9982', 'b64::JC50b2tlbg==::46b', 'never', 60 %}"},"metaSortKey":50,"isPrivate":false,"settingStoreCookies":true,"settingSendCookies":true,"settingDisableRenderRequestBody":false,"settingEncodeUrl":true,"settingRebuildPath":true,"settingFollowRedirects":"global","_type":"request"},{"_id":"req_bfbab1a68a16447bc5274a303bc3b7e2","parentId":"fld_272c4698dab0d3598ce10440e2cef3b5","modified":1673535440240,"created":1673535440240,"url":"{{ _.baseUrl }}\/profiles","name":"Update","description":"","method":"PUT","body":{"mimeType":"application\/json","text":"{\n\t\"id\": \"1d47e758-718f-4f8e-8d00-9199d3900cf5\",\n\t\"name\": \"Nome de perfis de Usu\u00e1rio\",\n\t\"disabled\": 1\n}"},"parameters":[],"headers":[{"name":"Content-Type","value":"application\/json","id":"pair_e699d513bceaceed6ee42d7bd47a8fa4"}],"authentication":{"type":"bearer","token":"{% response 'body', 'req_7ea653561d854b6e86c806b3c57b9982', 'b64::JC50b2tlbg==::46b', 'never', 60 %}"},"metaSortKey":60,"isPrivate":false,"settingStoreCookies":true,"settingSendCookies":true,"settingDisableRenderRequestBody":false,"settingEncodeUrl":true,"settingRebuildPath":true,"settingFollowRedirects":"global","_type":"request"},{"_id":"req_efef7501d9fbb2174bd858e8b1312d27","parentId":"fld_272c4698dab0d3598ce10440e2cef3b5","modified":1673535440240,"created":1673535440240,"url":"{{ _.baseUrl }}\/profiles\/1d47e758-718f-4f8e-8d00-9199d3900cf5","name":"Delete","description":"","method":"DELETE","body":[],"parameters":[],"headers":[],"authentication":{"type":"bearer","token":"{% response 'body', 'req_7ea653561d854b6e86c806b3c57b9982', 'b64::JC50b2tlbg==::46b', 'never', 60 %}"},"metaSortKey":70,"isPrivate":false,"settingStoreCookies":true,"settingSendCookies":true,"settingDisableRenderRequestBody":false,"settingEncodeUrl":true,"settingRebuildPath":true,"settingFollowRedirects":"global","_type":"request"},{"_id":"fld_96c5556fea047518c2edb2f06654b98c","parentId":"fld_a4a6c4454c2a5ac25870c411db2922e3","modified":1673535440240,"created":1673535440240,"name":"ProfileOptions","description":"","environment":[],"environmentPropertyOrder":null,"metaSortKey":"999004","_type":"request_group"},{"_id":"req_9fb92cb688aedba19ee3e1c546d4ab4e","parentId":"fld_96c5556fea047518c2edb2f06654b98c","modified":1673535440240,"created":1673535440240,"url":"{{ _.baseUrl }}\/profile-options","name":"Create","description":"","method":"POST","body":{"mimeType":"application\/json","text":"{\n\t\"profileId\": null,\n\t\"menuOptionId\": null,\n\t\"permitAll\": 1,\n\t\"permitCreate\": 1,\n\t\"permitRestore\": 1,\n\t\"permitUpdate\": 1,\n\t\"permitDelete\": 1,\n\t\"disabled\": 1\n}"},"parameters":[],"headers":[{"name":"Content-Type","value":"application\/json","id":"pair_ef4d91c86924973c28d85eb4a5769a9a"}],"authentication":{"type":"bearer","token":"{% response 'body', 'req_7ea653561d854b6e86c806b3c57b9982', 'b64::JC50b2tlbg==::46b', 'never', 60 %}"},"metaSortKey":10,"isPrivate":false,"settingStoreCookies":true,"settingSendCookies":true,"settingDisableRenderRequestBody":false,"settingEncodeUrl":true,"settingRebuildPath":true,"settingFollowRedirects":"global","_type":"request"},{"_id":"req_e5d3ce2ac1b6697163b4fbd478ac30ad","parentId":"fld_96c5556fea047518c2edb2f06654b98c","modified":1673535440240,"created":1673535440240,"url":"{{ _.baseUrl }}\/profile-options\/select","name":"Select","description":"","method":"POST","body":[],"parameters":[],"headers":[{"name":"Content-Type","value":"application\/json","id":"pair_0e5fa9a0c217d27213bc189cbabc69d4"}],"authentication":{"type":"bearer","token":"{% response 'body', 'req_7ea653561d854b6e86c806b3c57b9982', 'b64::JC50b2tlbg==::46b', 'never', 60 %}"},"metaSortKey":30,"isPrivate":false,"settingStoreCookies":true,"settingSendCookies":true,"settingDisableRenderRequestBody":false,"settingEncodeUrl":true,"settingRebuildPath":true,"settingFollowRedirects":"global","_type":"request"},{"_id":"req_b400571db9780122dfeaf277e1bff435","parentId":"fld_96c5556fea047518c2edb2f06654b98c","modified":1673535440240,"created":1673535440240,"url":"{{ _.baseUrl }}\/profile-options\/list","name":"List","description":"","method":"POST","body":{"mimeType":"application\/json","text":"{\n\t\"search\": \"\",\n\t\"rowsPerPage\": 10,\n\t\"page\": 0,\n\t\"columnOrder\": [\"ASC\", \"ASC\"]\n}"},"parameters":[],"headers":[{"name":"Content-Type","value":"application\/json","id":"pair_e99b9aafd20152c901ba55fd74cd7d46"}],"authentication":{"type":"bearer","token":"{% response 'body', 'req_7ea653561d854b6e86c806b3c57b9982', 'b64::JC50b2tlbg==::46b', 'never', 60 %}"},"metaSortKey":20,"isPrivate":false,"settingStoreCookies":true,"settingSendCookies":true,"settingDisableRenderRequestBody":false,"settingEncodeUrl":true,"settingRebuildPath":true,"settingFollowRedirects":"global","_type":"request"},{"_id":"req_d71ed787b13d7e1c420dc0ee05bdc5e2","parentId":"fld_96c5556fea047518c2edb2f06654b98c","modified":1673535440240,"created":1673535440240,"url":"{{ _.baseUrl }}\/profile-options\/count","name":"Count","description":"","method":"POST","body":{"mimeType":"application\/json","text":"{\n\t\"search\": \"\"\n}"},"parameters":[],"headers":[{"name":"Content-Type","value":"application\/json","id":"pair_c67e52331f028400148d52231d605684"}],"authentication":{"type":"bearer","token":"{% response 'body', 'req_7ea653561d854b6e86c806b3c57b9982', 'b64::JC50b2tlbg==::46b', 'never', 60 %}"},"metaSortKey":40,"isPrivate":false,"settingStoreCookies":true,"settingSendCookies":true,"settingDisableRenderRequestBody":false,"settingEncodeUrl":true,"settingRebuildPath":true,"settingFollowRedirects":"global","_type":"request"},{"_id":"req_934b36dbe6b0f3141ad46fd6e189959c","parentId":"fld_96c5556fea047518c2edb2f06654b98c","modified":1673535440240,"created":1673535440240,"url":"{{ _.baseUrl }}\/profile-options\/1d47e758-718f-4f8e-8d00-9199d3900cf5","name":"Get","description":"","method":"GET","body":[],"parameters":[],"headers":[],"authentication":{"type":"bearer","token":"{% response 'body', 'req_7ea653561d854b6e86c806b3c57b9982', 'b64::JC50b2tlbg==::46b', 'never', 60 %}"},"metaSortKey":50,"isPrivate":false,"settingStoreCookies":true,"settingSendCookies":true,"settingDisableRenderRequestBody":false,"settingEncodeUrl":true,"settingRebuildPath":true,"settingFollowRedirects":"global","_type":"request"},{"_id":"req_0ef8ec53ea5c0e668fef5212b176e251","parentId":"fld_96c5556fea047518c2edb2f06654b98c","modified":1673535440240,"created":1673535440240,"url":"{{ _.baseUrl }}\/profile-options","name":"Update","description":"","method":"PUT","body":{"mimeType":"application\/json","text":"{\n\t\"id\": \"1d47e758-718f-4f8e-8d00-9199d3900cf5\",\n\t\"profileId\": null,\n\t\"menuOptionId\": null,\n\t\"permitAll\": 1,\n\t\"permitCreate\": 1,\n\t\"permitRestore\": 1,\n\t\"permitUpdate\": 1,\n\t\"permitDelete\": 1,\n\t\"disabled\": 1\n}"},"parameters":[],"headers":[{"name":"Content-Type","value":"application\/json","id":"pair_583ecefc215a4aeefca9acf02a3464c4"}],"authentication":{"type":"bearer","token":"{% response 'body', 'req_7ea653561d854b6e86c806b3c57b9982', 'b64::JC50b2tlbg==::46b', 'never', 60 %}"},"metaSortKey":60,"isPrivate":false,"settingStoreCookies":true,"settingSendCookies":true,"settingDisableRenderRequestBody":false,"settingEncodeUrl":true,"settingRebuildPath":true,"settingFollowRedirects":"global","_type":"request"},{"_id":"req_799e3a8a8dad0e591d5e9662265c9cf9","parentId":"fld_96c5556fea047518c2edb2f06654b98c","modified":1673535440240,"created":1673535440240,"url":"{{ _.baseUrl }}\/profile-options\/1d47e758-718f-4f8e-8d00-9199d3900cf5","name":"Delete","description":"","method":"DELETE","body":[],"parameters":[],"headers":[],"authentication":{"type":"bearer","token":"{% response 'body', 'req_7ea653561d854b6e86c806b3c57b9982', 'b64::JC50b2tlbg==::46b', 'never', 60 %}"},"metaSortKey":70,"isPrivate":false,"settingStoreCookies":true,"settingSendCookies":true,"settingDisableRenderRequestBody":false,"settingEncodeUrl":true,"settingRebuildPath":true,"settingFollowRedirects":"global","_type":"request"},{"_id":"fld_ffb16d3c925d329657cb5d35c5a4d6c9","parentId":"fld_a4a6c4454c2a5ac25870c411db2922e3","modified":1673535440240,"created":1673535440240,"name":"UsersProfiles","description":"","environment":[],"environmentPropertyOrder":null,"metaSortKey":"999005","_type":"request_group"},{"_id":"req_44e971f4a1b3179be4f7f41377cf802e","parentId":"fld_ffb16d3c925d329657cb5d35c5a4d6c9","modified":1673535440240,"created":1673535440240,"url":"{{ _.baseUrl }}\/users-profiles","name":"Create","description":"","method":"POST","body":{"mimeType":"application\/json","text":"{\n\t\"userId\": null,\n\t\"profileId\": null\n}"},"parameters":[],"headers":[{"name":"Content-Type","value":"application\/json","id":"pair_ecb2c932875800a38a26b7d37f21d893"}],"authentication":{"type":"bearer","token":"{% response 'body', 'req_7ea653561d854b6e86c806b3c57b9982', 'b64::JC50b2tlbg==::46b', 'never', 60 %}"},"metaSortKey":10,"isPrivate":false,"settingStoreCookies":true,"settingSendCookies":true,"settingDisableRenderRequestBody":false,"settingEncodeUrl":true,"settingRebuildPath":true,"settingFollowRedirects":"global","_type":"request"},{"_id":"req_5277668bb34ebd8754a8b9e3674b2a9a","parentId":"fld_ffb16d3c925d329657cb5d35c5a4d6c9","modified":1673535440240,"created":1673535440240,"url":"{{ _.baseUrl }}\/users-profiles\/select","name":"Select","description":"","method":"POST","body":[],"parameters":[],"headers":[{"name":"Content-Type","value":"application\/json","id":"pair_819de4e17c4c0e7de45586c93befae5a"}],"authentication":{"type":"bearer","token":"{% response 'body', 'req_7ea653561d854b6e86c806b3c57b9982', 'b64::JC50b2tlbg==::46b', 'never', 60 %}"},"metaSortKey":30,"isPrivate":false,"settingStoreCookies":true,"settingSendCookies":true,"settingDisableRenderRequestBody":false,"settingEncodeUrl":true,"settingRebuildPath":true,"settingFollowRedirects":"global","_type":"request"},{"_id":"req_9843c11433c2a46a0f7ce1f365b5e7c8","parentId":"fld_ffb16d3c925d329657cb5d35c5a4d6c9","modified":1673535440240,"created":1673535440240,"url":"{{ _.baseUrl }}\/users-profiles\/list","name":"List","description":"","method":"POST","body":{"mimeType":"application\/json","text":"{\n\t\"search\": \"\",\n\t\"rowsPerPage\": 10,\n\t\"page\": 0,\n\t\"columnOrder\": [\"ASC\", \"ASC\"]\n}"},"parameters":[],"headers":[{"name":"Content-Type","value":"application\/json","id":"pair_7d0e7172f63cc774c3fc50e488bb6008"}],"authentication":{"type":"bearer","token":"{% response 'body', 'req_7ea653561d854b6e86c806b3c57b9982', 'b64::JC50b2tlbg==::46b', 'never', 60 %}"},"metaSortKey":20,"isPrivate":false,"settingStoreCookies":true,"settingSendCookies":true,"settingDisableRenderRequestBody":false,"settingEncodeUrl":true,"settingRebuildPath":true,"settingFollowRedirects":"global","_type":"request"},{"_id":"req_48c9a7ed92d7b70e6808725231b41d44","parentId":"fld_ffb16d3c925d329657cb5d35c5a4d6c9","modified":1673535440240,"created":1673535440240,"url":"{{ _.baseUrl }}\/users-profiles\/count","name":"Count","description":"","method":"POST","body":{"mimeType":"application\/json","text":"{\n\t\"search\": \"\"\n}"},"parameters":[],"headers":[{"name":"Content-Type","value":"application\/json","id":"pair_65f6785617de4d7e4a7995212b71a26d"}],"authentication":{"type":"bearer","token":"{% response 'body', 'req_7ea653561d854b6e86c806b3c57b9982', 'b64::JC50b2tlbg==::46b', 'never', 60 %}"},"metaSortKey":40,"isPrivate":false,"settingStoreCookies":true,"settingSendCookies":true,"settingDisableRenderRequestBody":false,"settingEncodeUrl":true,"settingRebuildPath":true,"settingFollowRedirects":"global","_type":"request"},{"_id":"req_c6609f3176102a49b0afa97962eee565","parentId":"fld_ffb16d3c925d329657cb5d35c5a4d6c9","modified":1673535440240,"created":1673535440240,"url":"{{ _.baseUrl }}\/users-profiles\/1d47e758-718f-4f8e-8d00-9199d3900cf5","name":"Get","description":"","method":"GET","body":[],"parameters":[],"headers":[],"authentication":{"type":"bearer","token":"{% response 'body', 'req_7ea653561d854b6e86c806b3c57b9982', 'b64::JC50b2tlbg==::46b', 'never', 60 %}"},"metaSortKey":50,"isPrivate":false,"settingStoreCookies":true,"settingSendCookies":true,"settingDisableRenderRequestBody":false,"settingEncodeUrl":true,"settingRebuildPath":true,"settingFollowRedirects":"global","_type":"request"},{"_id":"req_81b5dcdcb970f9a99be0ce73a5ebd065","parentId":"fld_ffb16d3c925d329657cb5d35c5a4d6c9","modified":1673535440240,"created":1673535440240,"url":"{{ _.baseUrl }}\/users-profiles","name":"Update","description":"","method":"PUT","body":{"mimeType":"application\/json","text":"{\n\t\"id\": \"1d47e758-718f-4f8e-8d00-9199d3900cf5\",\n\t\"userId\": null,\n\t\"profileId\": null\n}"},"parameters":[],"headers":[{"name":"Content-Type","value":"application\/json","id":"pair_81ef9be3fa96c226844868cb641b2990"}],"authentication":{"type":"bearer","token":"{% response 'body', 'req_7ea653561d854b6e86c806b3c57b9982', 'b64::JC50b2tlbg==::46b', 'never', 60 %}"},"metaSortKey":60,"isPrivate":false,"settingStoreCookies":true,"settingSendCookies":true,"settingDisableRenderRequestBody":false,"settingEncodeUrl":true,"settingRebuildPath":true,"settingFollowRedirects":"global","_type":"request"},{"_id":"req_c2edb427be8639784e3734aa22ef2dbb","parentId":"fld_ffb16d3c925d329657cb5d35c5a4d6c9","modified":1673535440240,"created":1673535440240,"url":"{{ _.baseUrl }}\/users-profiles\/1d47e758-718f-4f8e-8d00-9199d3900cf5","name":"Delete","description":"","method":"DELETE","body":[],"parameters":[],"headers":[],"authentication":{"type":"bearer","token":"{% response 'body', 'req_7ea653561d854b6e86c806b3c57b9982', 'b64::JC50b2tlbg==::46b', 'never', 60 %}"},"metaSortKey":70,"isPrivate":false,"settingStoreCookies":true,"settingSendCookies":true,"settingDisableRenderRequestBody":false,"settingEncodeUrl":true,"settingRebuildPath":true,"settingFollowRedirects":"global","_type":"request"},{"_id":"fld_159bac3b6e91ddc9d91faf5f90481522","parentId":"fld_a4a6c4454c2a5ac25870c411db2922e3","modified":1673535440240,"created":1673535440240,"name":"Navigations","description":"","environment":[],"environmentPropertyOrder":null,"metaSortKey":"999006","_type":"request_group"},{"_id":"req_5db8ca1e7d564245e47bcf3129bc6b86","parentId":"fld_159bac3b6e91ddc9d91faf5f90481522","modified":1673535440240,"created":1673535440240,"url":"{{ _.baseUrl }}\/navigations","name":"Create","description":"","method":"POST","body":{"mimeType":"application\/json","text":"{\n\t\"userId\": null,\n\t\"navigationDate\": \"Data de navega\u00e7\u00e3o\",\n\t\"route\": \"Rota de navega\u00e7\u00e3o\"\n}"},"parameters":[],"headers":[{"name":"Content-Type","value":"application\/json","id":"pair_ea33ef4b3ac7c2ac3d7614fabb1a6b5e"}],"authentication":{"type":"bearer","token":"{% response 'body', 'req_7ea653561d854b6e86c806b3c57b9982', 'b64::JC50b2tlbg==::46b', 'never', 60 %}"},"metaSortKey":10,"isPrivate":false,"settingStoreCookies":true,"settingSendCookies":true,"settingDisableRenderRequestBody":false,"settingEncodeUrl":true,"settingRebuildPath":true,"settingFollowRedirects":"global","_type":"request"},{"_id":"req_c276135b73eec12d5f06985d01b5da66","parentId":"fld_159bac3b6e91ddc9d91faf5f90481522","modified":1673535440240,"created":1673535440240,"url":"{{ _.baseUrl }}\/navigations\/select","name":"Select","description":"","method":"POST","body":[],"parameters":[],"headers":[{"name":"Content-Type","value":"application\/json","id":"pair_118045a6e0599ed9cd0aeb938a4bc440"}],"authentication":{"type":"bearer","token":"{% response 'body', 'req_7ea653561d854b6e86c806b3c57b9982', 'b64::JC50b2tlbg==::46b', 'never', 60 %}"},"metaSortKey":30,"isPrivate":false,"settingStoreCookies":true,"settingSendCookies":true,"settingDisableRenderRequestBody":false,"settingEncodeUrl":true,"settingRebuildPath":true,"settingFollowRedirects":"global","_type":"request"},{"_id":"req_6aae615722d5b9329cd60b470a607613","parentId":"fld_159bac3b6e91ddc9d91faf5f90481522","modified":1673535440240,"created":1673535440240,"url":"{{ _.baseUrl }}\/navigations\/list","name":"List","description":"","method":"POST","body":{"mimeType":"application\/json","text":"{\n\t\"search\": \"\",\n\t\"rowsPerPage\": 10,\n\t\"page\": 0,\n\t\"columnOrder\": [\"ASC\", \"ASC\"]\n}"},"parameters":[],"headers":[{"name":"Content-Type","value":"application\/json","id":"pair_585783122414f73f85499e6c92489cc1"}],"authentication":{"type":"bearer","token":"{% response 'body', 'req_7ea653561d854b6e86c806b3c57b9982', 'b64::JC50b2tlbg==::46b', 'never', 60 %}"},"metaSortKey":20,"isPrivate":false,"settingStoreCookies":true,"settingSendCookies":true,"settingDisableRenderRequestBody":false,"settingEncodeUrl":true,"settingRebuildPath":true,"settingFollowRedirects":"global","_type":"request"},{"_id":"req_7e4985bdad8a827af9193e5de95ad2e5","parentId":"fld_159bac3b6e91ddc9d91faf5f90481522","modified":1673535440240,"created":1673535440240,"url":"{{ _.baseUrl }}\/navigations\/count","name":"Count","description":"","method":"POST","body":{"mimeType":"application\/json","text":"{\n\t\"search\": \"\"\n}"},"parameters":[],"headers":[{"name":"Content-Type","value":"application\/json","id":"pair_9a2031d4b691dcf264bf228394d0fa46"}],"authentication":{"type":"bearer","token":"{% response 'body', 'req_7ea653561d854b6e86c806b3c57b9982', 'b64::JC50b2tlbg==::46b', 'never', 60 %}"},"metaSortKey":40,"isPrivate":false,"settingStoreCookies":true,"settingSendCookies":true,"settingDisableRenderRequestBody":false,"settingEncodeUrl":true,"settingRebuildPath":true,"settingFollowRedirects":"global","_type":"request"},{"_id":"req_faa0893e8b99ef7ee8fe9454be0c5839","parentId":"fld_159bac3b6e91ddc9d91faf5f90481522","modified":1673535440240,"created":1673535440240,"url":"{{ _.baseUrl }}\/navigations\/1d47e758-718f-4f8e-8d00-9199d3900cf5","name":"Get","description":"","method":"GET","body":[],"parameters":[],"headers":[],"authentication":{"type":"bearer","token":"{% response 'body', 'req_7ea653561d854b6e86c806b3c57b9982', 'b64::JC50b2tlbg==::46b', 'never', 60 %}"},"metaSortKey":50,"isPrivate":false,"settingStoreCookies":true,"settingSendCookies":true,"settingDisableRenderRequestBody":false,"settingEncodeUrl":true,"settingRebuildPath":true,"settingFollowRedirects":"global","_type":"request"},{"_id":"req_3a3e23dc3f99a332b97fff5ea6a1ff97","parentId":"fld_159bac3b6e91ddc9d91faf5f90481522","modified":1673535440240,"created":1673535440240,"url":"{{ _.baseUrl }}\/navigations","name":"Update","description":"","method":"PUT","body":{"mimeType":"application\/json","text":"{\n\t\"id\": \"1d47e758-718f-4f8e-8d00-9199d3900cf5\",\n\t\"userId\": null,\n\t\"navigationDate\": \"Data de navega\u00e7\u00e3o\",\n\t\"route\": \"Rota de navega\u00e7\u00e3o\"\n}"},"parameters":[],"headers":[{"name":"Content-Type","value":"application\/json","id":"pair_76f44d0c465a0dbab0c3c14e5caf96bd"}],"authentication":{"type":"bearer","token":"{% response 'body', 'req_7ea653561d854b6e86c806b3c57b9982', 'b64::JC50b2tlbg==::46b', 'never', 60 %}"},"metaSortKey":60,"isPrivate":false,"settingStoreCookies":true,"settingSendCookies":true,"settingDisableRenderRequestBody":false,"settingEncodeUrl":true,"settingRebuildPath":true,"settingFollowRedirects":"global","_type":"request"},{"_id":"req_1dadb1321fdf341babb92b6f3a3d270e","parentId":"fld_159bac3b6e91ddc9d91faf5f90481522","modified":1673535440240,"created":1673535440240,"url":"{{ _.baseUrl }}\/navigations\/1d47e758-718f-4f8e-8d00-9199d3900cf5","name":"Delete","description":"","method":"DELETE","body":[],"parameters":[],"headers":[],"authentication":{"type":"bearer","token":"{% response 'body', 'req_7ea653561d854b6e86c806b3c57b9982', 'b64::JC50b2tlbg==::46b', 'never', 60 %}"},"metaSortKey":70,"isPrivate":false,"settingStoreCookies":true,"settingSendCookies":true,"settingDisableRenderRequestBody":false,"settingEncodeUrl":true,"settingRebuildPath":true,"settingFollowRedirects":"global","_type":"request"},{"_id":"jar_5477311fd8d74443b1ae8286743365aa","parentId":"wrk_46703ad94c413e29ffa24f25275d130d","modified":1673535440240,"created":1673535440240,"name":"Default Jar","cookies":[],"_type":"cookie_jar"},{"_id":"spc_e9a2d156a90cd7ab0d89d6e0f3ffc21e","parentId":"wrk_46703ad94c413e29ffa24f25275d130d","modified":1673535440240,"created":1673535440240,"fileName":"basic","contents":"","contentType":"yaml","_type":"api_spec"}]}